indices/__init__.py
indices/g_index.py
indices/h_index.py
indices/psi_index.py
indices/x_index.py
scientometrics-0.1.0.dist-info/LICENSE.txt
scientometrics-0.1.0.dist-info/METADATA
scientometrics-0.1.0.dist-info/WHEEL
scientometrics-0.1.0.dist-info/top_level.txt
scientometrics-0.1.0.dist-info/RECORD
