Metadata-Version: 2.1
Name: scientometrics
Version: 0.1.0
Summary: A package for calculating scientometric indices
Home-page: https://github.com/abhirupnandy/scientometrics
Author: Abhirup Nandy, Nilabhra Rohan Das
Author-email: abhirupnandy.rocks@gmail.com, nr.das@yahoo.com
Project-URL: Bug Tracker, https://github.com/abhirupnandy/scientometrics/issues
Classifier: Programming Language :: Python :: 3
Classifier: License :: OSI Approved :: MIT License
Classifier: Operating System :: OS Independent
Requires-Python: >=3.6
License-File: LICENSE.txt
